{"0": "User Registration & Verification", "1": "System & Branch Monitoring", "2": "Root Layout & Typography", "3": "Cart API Routes", "4": "Landing Grid & Sidebar", "5": "Product Catalog Toolbar & Actions", "6": "Email Verification Schema", "7": "Inventory Flow & KPI Metrics", "8": "Cashier Shopping Cart", "9": "Customer Dashboard Navigation & Header", "10": "Cashier Transaction History", "11": "Customer Checkout & Cart Store", "12": "Staff Inventory & KPI Cards", "13": "Staff Payment & Pickup Lists", "14": "Dashboard Sidebars & Topbar", "15": "Staff Pickup Confirmation Modal", "16": "Staff Transaction Feed & Table", "17": "BentaHub System Architecture Docs", "18": "Staff Stock Management", "19": "Admin User Management Modals", "20": "Admin History & Transaction Table", "21": "Customer Orders & History", "22": "Customer Catalog Sidebar & Pagination", "23": "Customer Reservation Summary", "24": "Branch Inventory Schema", "25": "Orders Schema", "26": "Admin Overview Analytics", "27": "Admin Reservations & Users Panel", "28": "Admin Payment History Modals", "29": "Admin Sales Analytics Actions", "30": "Cashier Layout & Navigation", "31": "Admin Notifications Feed", "32": "Cashier Payments Panel", "33": "Cashier Product Stock View", "34": "Customer Notifications Feed", "35": "Transactions Schema", "36": "Admin Database Seeding", "37": "Authentication & Setup Documentation", "38": "Notifications Hook & Zustand Store", "39": "Admin Sidebar Layout", "40": "Staff Notifications Feed", "41": "Products Schema", "42": "Cashier Notifications Feed", "43": "Admin Pickups & Metrics", "44": "Admin Branch Stock Table", "45": "Docker Configuration & Setup", "46": "Notifications Types", "47": "Authentication Layout", "48": "Database Connection Check Scripts", "49": "Database Table Creation Scripts", "50": "Product Database Seeding Scripts", "51": "Database Setup Shell Scripts", "52": "ESLint Rules Configuration", "53": "Logout API Route", "54": "PostCSS Configuration", "55": "Database Connection Diagnostic Tools", "56": "Product Verification Scripts", "57": "User Verification Scripts", "58": "User Schema Check Scripts", "59": "Global Tables Initialization", "60": "Test User Generation", "61": "Tables Setup Helper", "62": "Admin Settings Page", "63": "Proxy Handler Configuration", "64": "Centralized Monitoring Entry", "65": "Customer System Status Documentation", "66": "Drizzle Configuration", "67": "QR POS Entry Point", "68": "Reservations Entry Point", "69": "Email Verification Schema", "70": "PowerShell DB Setup Script"}